rotpy/__init__.py
rotpy/_interface.cp39-win_amd64.pyd
rotpy/_interface.pxd
rotpy/_interface.pyx
rotpy/camera.cp39-win_amd64.pyd
rotpy/camera.pxd
rotpy/camera.pyx
rotpy/camera_nodes.cp39-win_amd64.pyd
rotpy/camera_nodes.pxd
rotpy/camera_nodes.pyx
rotpy/image.cp39-win_amd64.pyd
rotpy/image.pxd
rotpy/image.pyx
rotpy/node.cp39-win_amd64.pyd
rotpy/node.pxd
rotpy/node.pyx
rotpy/system.cp39-win_amd64.pyd
rotpy/system.pxd
rotpy/system.pyx
rotpy/system_nodes.cp39-win_amd64.pyd
rotpy/system_nodes.pxd
rotpy/system_nodes.pyx
rotpy/utils.py
rotpy/_cam_defs/__init__.py
rotpy/_cam_defs/_cam_defs1.cp39-win_amd64.pyd
rotpy/_cam_defs/_cam_defs1.pxd
rotpy/_cam_defs/_cam_defs1.pyx
rotpy/_cam_defs/_cam_defs2.cp39-win_amd64.pyd
rotpy/_cam_defs/_cam_defs2.pxd
rotpy/_cam_defs/_cam_defs2.pyx
rotpy/_cam_defs/_cam_defs3.cp39-win_amd64.pyd
rotpy/_cam_defs/_cam_defs3.pxd
rotpy/_cam_defs/_cam_defs3.pyx
rotpy/_cam_defs/_cam_defs4.cp39-win_amd64.pyd
rotpy/_cam_defs/_cam_defs4.pxd
rotpy/_cam_defs/_cam_defs4.pyx
rotpy/_cam_defs/_cam_defs5.cp39-win_amd64.pyd
rotpy/_cam_defs/_cam_defs5.pxd
rotpy/_cam_defs/_cam_defs5.pyx
rotpy/includes/CameraDefs1.pxi
rotpy/includes/CameraDefs2.pxi
rotpy/includes/CameraDefs3.pxi
rotpy/includes/CameraDefs4.pxi
rotpy/includes/CameraDefs5.pxi
rotpy/includes/SpinnakerDefs.pxi
rotpy/includes/TransportLayerDefs.pxi
rotpy/includes/Types.pxi
rotpy/includes/rotpy_enum_wrapper.h
rotpy/includes/rotpy_event.h
rotpy/includes/spinnaker.pxi
rotpy/includes/spinnaker_exception.h
rotpy/names/__init__.py
rotpy/names/camera.cp39-win_amd64.pyd
rotpy/names/camera.pyx
rotpy/names/geni.cp39-win_amd64.pyd
rotpy/names/geni.pyx
rotpy/names/spin.cp39-win_amd64.pyd
rotpy/names/spin.pyx
rotpy/names/tl.cp39-win_amd64.pyd
rotpy/names/tl.pyx
rotpy/test/__init__.py
rotpy/test/test_api.py
rotpy-0.2.1.data/data/share/rotpy/spinnaker/bin/GCBase_MD_VC140_v3_0.dll
rotpy-0.2.1.data/data/share/rotpy/spinnaker/bin/GenApi_MD_VC140_v3_0.dll
rotpy-0.2.1.data/data/share/rotpy/spinnaker/bin/Log_MD_VC140_v3_0.dll
rotpy-0.2.1.dist-info/LICENSE
rotpy-0.2.1.dist-info/METADATA
rotpy-0.2.1.dist-info/WHEEL
rotpy-0.2.1.dist-info/top_level.txt
rotpy-0.2.1.dist-info/RECORD
