Metadata-Version: 2.1
Name: rotpy
Version: 0.2.1
Summary: Cython bindings for the Spinnaker camera control API.
Home-page: https://matham.github.io/rotpy/
Author: Matthew Einhorn
License: MIT
Project-URL: Documentation, https://matham.github.io/rotpy/
Project-URL: Source, https://github.com/matham/rotpy/
Classifier: License :: OSI Approved :: MIT License
Classifier: Topic :: Multimedia :: Graphics :: Capture :: Digital Camera
Classifier: Topic :: Multimedia :: Graphics :: Capture
Classifier: Programming Language :: Python :: 3.7
Classifier: Programming Language :: Python :: 3.8
Classifier: Programming Language :: Python :: 3.9
Classifier: Programming Language :: Python :: 3.10
Classifier: Programming Language :: Python :: 3.11
Classifier: Operating System :: Microsoft :: Windows
Classifier: Operating System :: POSIX :: Linux
Classifier: Operating System :: MacOS
Classifier: Intended Audience :: Developers
License-File: LICENSE
Provides-Extra: doc
Requires-Dist: sphinx-copybutton ; extra == 'doc'
Requires-Dist: sphinx-rtd-theme ; extra == 'doc'
Requires-Dist: sphinx ; extra == 'doc'
Requires-Dist: cython ; extra == 'doc'
Requires-Dist: autodocsumm ; extra == 'doc'
Provides-Extra: test
Requires-Dist: pytest ; extra == 'test'
